{
    "1": {
        "R": "FF",
        "G": 0,
        "B": 0,
        "r": 255,
        "g": 0,
        "b": 0
    },
    "0": {
        "R": 0,
        "G": 0,
        "B": 0,
        "r": 0,
        "g": 0,
        "b": 0
    },
    "3": {
        "R": 0,
        "G": "FF",
        "B": 0,
        "r": 0,
        "g": 255,
        "b": 0
    },
    "2": {
        "R": "FF",
        "G": "FF",
        "B": 0,
        "r": 255,
        "g": 255,
        "b": 0
    },
    "5": {
        "R": 0,
        "G": 0,
        "B": "FF",
        "r": 0,
        "g": 0,
        "b": 255
    },
    "4": {
        "R": 0,
        "G": "FF",
        "B": "FF",
        "r": 0,
        "g": 255,
        "b": 255
    },
    "7": {
        "R": "FF",
        "G": "FF",
        "B": "FF",
        "r": 255,
        "g": 255,
        "b": 255
    },
    "6": {
        "R": "FF",
        "G": 0,
        "B": "FF",
        "r": 255,
        "g": 0,
        "b": 255
    },
    "9": {
        "R": 80,
        "G": 80,
        "B": 80,
        "r": 128,
        "g": 128,
        "b": 128
    },
    "8": {
        "R": 41,
        "G": 41,
        "B": 41,
        "r": 65,
        "g": 65,
        "b": 65
    },
    "11": {
        "R": "FF",
        "G": "AA",
        "B": "AA",
        "r": 255,
        "g": 170,
        "b": 170
    },
    "10": {
        "R": "FF",
        "G": 0,
        "B": 0,
        "r": 255,
        "g": 0,
        "b": 0
    },
    "13": {
        "R": "BD",
        "G": "7E",
        "B": "7E",
        "r": 189,
        "g": 126,
        "b": 126
    },
    "12": {
        "R": "BD",
        "G": 0,
        "B": 0,
        "r": 189,
        "g": 0,
        "b": 0
    },
    "15": {
        "R": 81,
        "G": 56,
        "B": 56,
        "r": 129,
        "g": 86,
        "b": 86
    },
    "14": {
        "R": 81,
        "G": 0,
        "B": 0,
        "r": 129,
        "g": 0,
        "b": 0
    },
    "17": {
        "R": 68,
        "G": 45,
        "B": 45,
        "r": 104,
        "g": 69,
        "b": 69
    },
    "16": {
        "R": 68,
        "G": 0,
        "B": 0,
        "r": 104,
        "g": 0,
        "b": 0
    },
    "19": {
        "R": "4F",
        "G": 35,
        "B": 35,
        "r": 79,
        "g": 53,
        "b": 53
    },
    "18": {
        "R": "4F",
        "G": 0,
        "B": 0,
        "r": 79,
        "g": 0,
        "b": 0
    },
    "21": {
        "R": "FF",
        "G": "BF",
        "B": "AA",
        "r": 255,
        "g": 191,
        "b": 170
    },
    "20": {
        "R": "FF",
        "G": "3F",
        "B": 0,
        "r": 255,
        "g": 63,
        "b": 0
    },
    "23": {
        "R": "BD",
        "G": "8D",
        "B": "7E",
        "r": 189,
        "g": 141,
        "b": 126
    },
    "22": {
        "R": "BD",
        "G": "2E",
        "B": 0,
        "r": 189,
        "g": 46,
        "b": 0
    },
    "24": {
        "R": 81,
        "G": "1F",
        "B": 0,
        "r": 129,
        "g": 31,
        "b": 0
    },
    "25": {
        "R": 81,
        "G": 60,
        "B": 56,
        "r": 129,
        "g": 96,
        "b": 86
    },
    "26": {
        "R": 68,
        "G": 19,
        "B": 0,
        "r": 104,
        "g": 25,
        "b": 0
    },
    "27": {
        "R": 68,
        "G": "4E",
        "B": 45,
        "r": 104,
        "g": 78,
        "b": 69
    },
    "28": {
        "R": "4F",
        "G": 13,
        "B": 0,
        "r": 79,
        "g": 19,
        "b": 0
    },
    "29": {
        "R": "4F",
        "G": "3B",
        "B": 35,
        "r": 79,
        "g": 59,
        "b": 53
    },
    "30": {
        "R": "FF",
        "G": "7F",
        "B": 0,
        "r": 255,
        "g": 127,
        "b": 0
    },
    "31": {
        "R": "FF",
        "G": "D4",
        "B": "AA",
        "r": 255,
        "g": 212,
        "b": 170
    },
    "32": {
        "R": "BD",
        "G": "5E",
        "B": 0,
        "r": 189,
        "g": 94,
        "b": 0
    },
    "33": {
        "R": "BD",
        "G": "9D",
        "B": "7E",
        "r": 189,
        "g": 157,
        "b": 126
    },
    "34": {
        "R": 81,
        "G": 40,
        "B": 0,
        "r": 129,
        "g": 64,
        "b": 0
    },
    "35": {
        "R": 81,
        "G": "6B",
        "B": 56,
        "r": 129,
        "g": 107,
        "b": 86
    },
    "36": {
        "R": 68,
        "G": 34,
        "B": 0,
        "r": 104,
        "g": 52,
        "b": 0
    },
    "37": {
        "R": 68,
        "G": 56,
        "B": 45,
        "r": 104,
        "g": 86,
        "b": 69
    },
    "38": {
        "R": "4F",
        "G": 27,
        "B": 0,
        "r": 79,
        "g": 39,
        "b": 0
    },
    "39": {
        "R": "4F",
        "G": 42,
        "B": 35,
        "r": 79,
        "g": 66,
        "b": 53
    },
    "40": {
        "R": "FF",
        "G": "BF",
        "B": 0,
        "r": 255,
        "g": 191,
        "b": 0
    },
    "41": {
        "R": "FF",
        "G": "EA",
        "B": "AA",
        "r": 255,
        "g": 234,
        "b": 170
    },
    "42": {
        "R": "BD",
        "G": "8D",
        "B": 0,
        "r": 189,
        "g": 141,
        "b": 0
    },
    "43": {
        "R": "BD",
        "G": "AD",
        "B": "7E",
        "r": 189,
        "g": 173,
        "b": 126
    },
    "44": {
        "R": 81,
        "G": 60,
        "B": 0,
        "r": 129,
        "g": 96,
        "b": 0
    },
    "45": {
        "R": 81,
        "G": 76,
        "B": 56,
        "r": 129,
        "g": 118,
        "b": 86
    },
    "46": {
        "R": 68,
        "G": "4E",
        "B": 0,
        "r": 104,
        "g": 78,
        "b": 0
    },
    "47": {
        "R": 68,
        "G": "5F",
        "B": 45,
        "r": 104,
        "g": 95,
        "b": 69
    },
    "48": {
        "R": "4F",
        "G": "3B",
        "B": 0,
        "r": 79,
        "g": 59,
        "b": 0
    },
    "49": {
        "R": "4F",
        "G": 49,
        "B": 35,
        "r": 79,
        "g": 73,
        "b": 53
    },
    "50": {
        "R": "FF",
        "G": "FF",
        "B": 0,
        "r": 255,
        "g": 255,
        "b": 0
    },
    "51": {
        "R": "FF",
        "G": "FF",
        "B": "AA",
        "r": 255,
        "g": 255,
        "b": 170
    },
    "52": {
        "R": "BD",
        "G": "BD",
        "B": 0,
        "r": 189,
        "g": 189,
        "b": 0
    },
    "53": {
        "R": "BD",
        "G": "BD",
        "B": "7E",
        "r": 189,
        "g": 189,
        "b": 126
    },
    "54": {
        "R": 81,
        "G": 81,
        "B": 0,
        "r": 129,
        "g": 129,
        "b": 0
    },
    "55": {
        "R": 81,
        "G": 81,
        "B": 56,
        "r": 129,
        "g": 129,
        "b": 86
    },
    "56": {
        "R": 68,
        "G": 68,
        "B": 0,
        "r": 104,
        "g": 104,
        "b": 0
    },
    "57": {
        "R": 68,
        "G": 68,
        "B": 45,
        "r": 104,
        "g": 104,
        "b": 69
    },
    "58": {
        "R": "4F",
        "G": "4F",
        "B": 0,
        "r": 79,
        "g": 79,
        "b": 0
    },
    "59": {
        "R": "4F",
        "G": "4F",
        "B": 35,
        "r": 79,
        "g": 79,
        "b": 53
    },
    "60": {
        "R": "BF",
        "G": "FF",
        "B": 0,
        "r": 191,
        "g": 255,
        "b": 0
    },
    "61": {
        "R": "EA",
        "G": "FF",
        "B": "AA",
        "r": 234,
        "g": 255,
        "b": 170
    },
    "62": {
        "R": "8D",
        "G": "BD",
        "B": 0,
        "r": 141,
        "g": 189,
        "b": 0
    },
    "63": {
        "R": "AD",
        "G": "BD",
        "B": "7E",
        "r": 173,
        "g": 189,
        "b": 126
    },
    "64": {
        "R": 60,
        "G": 81,
        "B": 0,
        "r": 96,
        "g": 129,
        "b": 0
    },
    "65": {
        "R": 76,
        "G": 81,
        "B": 56,
        "r": 118,
        "g": 129,
        "b": 86
    },
    "66": {
        "R": "4E",
        "G": 68,
        "B": 0,
        "r": 78,
        "g": 104,
        "b": 0
    },
    "67": {
        "R": "5F",
        "G": 68,
        "B": 45,
        "r": 95,
        "g": 104,
        "b": 69
    },
    "68": {
        "R": "3B",
        "G": "4F",
        "B": 0,
        "r": 59,
        "g": 79,
        "b": 0
    },
    "69": {
        "R": 49,
        "G": "4F",
        "B": 35,
        "r": 73,
        "g": 79,
        "b": 53
    },
    "70": {
        "R": "7F",
        "G": "FF",
        "B": 0,
        "r": 127,
        "g": 255,
        "b": 0
    },
    "71": {
        "R": "D4",
        "G": "FF",
        "B": "AA",
        "r": 212,
        "g": 255,
        "b": 170
    },
    "72": {
        "R": "5E",
        "G": "BD",
        "B": 0,
        "r": 94,
        "g": 189,
        "b": 0
    },
    "73": {
        "R": "9D",
        "G": "BD",
        "B": "7E",
        "r": 157,
        "g": 189,
        "b": 126
    },
    "74": {
        "R": 40,
        "G": 81,
        "B": 0,
        "r": 64,
        "g": 129,
        "b": 0
    },
    "75": {
        "R": "6B",
        "G": 81,
        "B": 56,
        "r": 107,
        "g": 129,
        "b": 86
    },
    "76": {
        "R": 34,
        "G": 68,
        "B": 0,
        "r": 52,
        "g": 104,
        "b": 0
    },
    "77": {
        "R": 56,
        "G": 68,
        "B": 45,
        "r": 86,
        "g": 104,
        "b": 69
    },
    "78": {
        "R": 27,
        "G": "4F",
        "B": 0,
        "r": 39,
        "g": 79,
        "b": 0
    },
    "79": {
        "R": 42,
        "G": "4F",
        "B": 35,
        "r": 66,
        "g": 79,
        "b": 53
    },
    "80": {
        "R": "3F",
        "G": "FF",
        "B": 0,
        "r": 63,
        "g": 255,
        "b": 0
    },
    "81": {
        "R": "BF",
        "G": "FF",
        "B": "AA",
        "r": 191,
        "g": 255,
        "b": 170
    },
    "82": {
        "R": "2E",
        "G": "BD",
        "B": 0,
        "r": 46,
        "g": 189,
        "b": 0
    },
    "83": {
        "R": "8D",
        "G": "BD",
        "B": "7E",
        "r": 141,
        "g": 189,
        "b": 126
    },
    "84": {
        "R": "1F",
        "G": 81,
        "B": 0,
        "r": 31,
        "g": 129,
        "b": 0
    },
    "85": {
        "R": 60,
        "G": 81,
        "B": 56,
        "r": 96,
        "g": 129,
        "b": 86
    },
    "86": {
        "R": 19,
        "G": 68,
        "B": 0,
        "r": 25,
        "g": 104,
        "b": 0
    },
    "87": {
        "R": "4E",
        "G": 68,
        "B": 45,
        "r": 78,
        "g": 104,
        "b": 69
    },
    "88": {
        "R": 13,
        "G": "4F",
        "B": 0,
        "r": 19,
        "g": 79,
        "b": 0
    },
    "89": {
        "R": "3B",
        "G": "4F",
        "B": 35,
        "r": 59,
        "g": 79,
        "b": 53
    },
    "90": {
        "R": 0,
        "G": "FF",
        "B": 0,
        "r": 0,
        "g": 255,
        "b": 0
    },
    "91": {
        "R": "AA",
        "G": "FF",
        "B": "AA",
        "r": 170,
        "g": 255,
        "b": 170
    },
    "92": {
        "R": 0,
        "G": "BD",
        "B": 0,
        "r": 0,
        "g": 189,
        "b": 0
    },
    "93": {
        "R": "7E",
        "G": "BD",
        "B": "7E",
        "r": 126,
        "g": 189,
        "b": 126
    },
    "94": {
        "R": 0,
        "G": 81,
        "B": 0,
        "r": 0,
        "g": 129,
        "b": 0
    },
    "95": {
        "R": 56,
        "G": 81,
        "B": 56,
        "r": 86,
        "g": 129,
        "b": 86
    },
    "96": {
        "R": 0,
        "G": 68,
        "B": 0,
        "r": 0,
        "g": 104,
        "b": 0
    },
    "97": {
        "R": 45,
        "G": 68,
        "B": 45,
        "r": 69,
        "g": 104,
        "b": 69
    },
    "98": {
        "R": 0,
        "G": "4F",
        "B": 0,
        "r": 0,
        "g": 79,
        "b": 0
    },
    "99": {
        "R": 35,
        "G": "4F",
        "B": 35,
        "r": 53,
        "g": 79,
        "b": 53
    },
    "100": {
        "R": 0,
        "G": "FF",
        "B": "3F",
        "r": 0,
        "g": 255,
        "b": 63
    },
    "101": {
        "R": "AA",
        "G": "FF",
        "B": "BF",
        "r": 170,
        "g": 255,
        "b": 191
    },
    "102": {
        "R": 0,
        "G": "BD",
        "B": "2E",
        "r": 0,
        "g": 189,
        "b": 46
    },
    "103": {
        "R": "7E",
        "G": "BD",
        "B": "8D",
        "r": 126,
        "g": 189,
        "b": 141
    },
    "104": {
        "R": 0,
        "G": 81,
        "B": "1F",
        "r": 0,
        "g": 129,
        "b": 31
    },
    "105": {
        "R": 56,
        "G": 81,
        "B": 60,
        "r": 86,
        "g": 129,
        "b": 96
    },
    "106": {
        "R": 0,
        "G": 68,
        "B": 19,
        "r": 0,
        "g": 104,
        "b": 25
    },
    "107": {
        "R": 45,
        "G": 68,
        "B": "4E",
        "r": 69,
        "g": 104,
        "b": 78
    },
    "108": {
        "R": 0,
        "G": "4F",
        "B": 13,
        "r": 0,
        "g": 79,
        "b": 19
    },
    "109": {
        "R": 35,
        "G": "4F",
        "B": "3B",
        "r": 53,
        "g": 79,
        "b": 59
    },
    "110": {
        "R": 0,
        "G": "FF",
        "B": "7F",
        "r": 0,
        "g": 255,
        "b": 127
    },
    "111": {
        "R": "AA",
        "G": "FF",
        "B": "D4",
        "r": 170,
        "g": 255,
        "b": 212
    },
    "112": {
        "R": 0,
        "G": "BD",
        "B": "5E",
        "r": 0,
        "g": 189,
        "b": 94
    },
    "113": {
        "R": "7E",
        "G": "BD",
        "B": "9D",
        "r": 126,
        "g": 189,
        "b": 157
    },
    "114": {
        "R": 0,
        "G": 81,
        "B": 40,
        "r": 0,
        "g": 129,
        "b": 64
    },
    "115": {
        "R": 56,
        "G": 81,
        "B": "6B",
        "r": 86,
        "g": 129,
        "b": 107
    },
    "116": {
        "R": 0,
        "G": 68,
        "B": 34,
        "r": 0,
        "g": 104,
        "b": 52
    },
    "117": {
        "R": 45,
        "G": 68,
        "B": 56,
        "r": 69,
        "g": 104,
        "b": 86
    },
    "118": {
        "R": 0,
        "G": "4F",
        "B": 27,
        "r": 0,
        "g": 79,
        "b": 39
    },
    "119": {
        "R": 35,
        "G": "4F",
        "B": 42,
        "r": 53,
        "g": 79,
        "b": 66
    },
    "120": {
        "R": 0,
        "G": "FF",
        "B": "BF",
        "r": 0,
        "g": 255,
        "b": 191
    },
    "121": {
        "R": "AA",
        "G": "FF",
        "B": "EA",
        "r": 170,
        "g": 255,
        "b": 234
    },
    "122": {
        "R": 0,
        "G": "BD",
        "B": "8D",
        "r": 0,
        "g": 189,
        "b": 141
    },
    "123": {
        "R": "7E",
        "G": "BD",
        "B": "AD",
        "r": 126,
        "g": 189,
        "b": 173
    },
    "124": {
        "R": 0,
        "G": 81,
        "B": 60,
        "r": 0,
        "g": 129,
        "b": 96
    },
    "125": {
        "R": 56,
        "G": 81,
        "B": 76,
        "r": 86,
        "g": 129,
        "b": 118
    },
    "126": {
        "R": 0,
        "G": 68,
        "B": "4E",
        "r": 0,
        "g": 104,
        "b": 78
    },
    "127": {
        "R": 45,
        "G": 68,
        "B": "5F",
        "r": 69,
        "g": 104,
        "b": 95
    },
    "128": {
        "R": 0,
        "G": "4F",
        "B": "3B",
        "r": 0,
        "g": 79,
        "b": 59
    },
    "129": {
        "R": 35,
        "G": "4F",
        "B": 49,
        "r": 53,
        "g": 79,
        "b": 73
    },
    "130": {
        "R": 0,
        "G": "FF",
        "B": "FF",
        "r": 0,
        "g": 255,
        "b": 255
    },
    "131": {
        "R": "AA",
        "G": "FF",
        "B": "FF",
        "r": 170,
        "g": 255,
        "b": 255
    },
    "132": {
        "R": 0,
        "G": "BD",
        "B": "BD",
        "r": 0,
        "g": 189,
        "b": 189
    },
    "133": {
        "R": "7E",
        "G": "BD",
        "B": "BD",
        "r": 126,
        "g": 189,
        "b": 189
    },
    "134": {
        "R": 0,
        "G": 81,
        "B": 81,
        "r": 0,
        "g": 129,
        "b": 129
    },
    "135": {
        "R": 56,
        "G": 81,
        "B": 81,
        "r": 86,
        "g": 129,
        "b": 129
    },
    "136": {
        "R": 0,
        "G": 68,
        "B": 68,
        "r": 0,
        "g": 104,
        "b": 104
    },
    "137": {
        "R": 45,
        "G": 68,
        "B": 68,
        "r": 69,
        "g": 104,
        "b": 104
    },
    "138": {
        "R": 0,
        "G": "4F",
        "B": "4F",
        "r": 0,
        "g": 79,
        "b": 79
    },
    "139": {
        "R": 35,
        "G": "4F",
        "B": "4F",
        "r": 53,
        "g": 79,
        "b": 79
    },
    "140": {
        "R": 0,
        "G": "BF",
        "B": "FF",
        "r": 0,
        "g": 191,
        "b": 255
    },
    "141": {
        "R": "AA",
        "G": "EA",
        "B": "FF",
        "r": 170,
        "g": 234,
        "b": 255
    },
    "142": {
        "R": 0,
        "G": "8D",
        "B": "BD",
        "r": 0,
        "g": 141,
        "b": 189
    },
    "143": {
        "R": "7E",
        "G": "AD",
        "B": "BD",
        "r": 126,
        "g": 173,
        "b": 189
    },
    "144": {
        "R": 0,
        "G": 60,
        "B": 81,
        "r": 0,
        "g": 96,
        "b": 129
    },
    "145": {
        "R": 56,
        "G": 76,
        "B": 81,
        "r": 86,
        "g": 118,
        "b": 129
    },
    "146": {
        "R": 0,
        "G": "4E",
        "B": 68,
        "r": 0,
        "g": 78,
        "b": 104
    },
    "147": {
        "R": 45,
        "G": "5F",
        "B": 68,
        "r": 69,
        "g": 95,
        "b": 104
    },
    "148": {
        "R": 0,
        "G": "3B",
        "B": "4F",
        "r": 0,
        "g": 59,
        "b": 79
    },
    "149": {
        "R": 35,
        "G": 49,
        "B": "4F",
        "r": 53,
        "g": 73,
        "b": 79
    },
    "150": {
        "R": 0,
        "G": "7F",
        "B": "FF",
        "r": 0,
        "g": 127,
        "b": 255
    },
    "151": {
        "R": "AA",
        "G": "D4",
        "B": "FF",
        "r": 170,
        "g": 212,
        "b": 255
    },
    "152": {
        "R": 0,
        "G": "5E",
        "B": "BD",
        "r": 0,
        "g": 94,
        "b": 189
    },
    "153": {
        "R": "7E",
        "G": "9D",
        "B": "BD",
        "r": 126,
        "g": 157,
        "b": 189
    },
    "154": {
        "R": 0,
        "G": 40,
        "B": 81,
        "r": 0,
        "g": 64,
        "b": 129
    },
    "155": {
        "R": 56,
        "G": "6B",
        "B": 81,
        "r": 86,
        "g": 107,
        "b": 129
    },
    "156": {
        "R": 0,
        "G": 34,
        "B": 68,
        "r": 0,
        "g": 52,
        "b": 104
    },
    "157": {
        "R": 45,
        "G": 56,
        "B": 68,
        "r": 69,
        "g": 86,
        "b": 104
    },
    "158": {
        "R": 0,
        "G": 27,
        "B": "4F",
        "r": 0,
        "g": 39,
        "b": 79
    },
    "159": {
        "R": 35,
        "G": 42,
        "B": "4F",
        "r": 53,
        "g": 66,
        "b": 79
    },
    "160": {
        "R": 0,
        "G": "3F",
        "B": "FF",
        "r": 0,
        "g": 63,
        "b": 255
    },
    "161": {
        "R": "AA",
        "G": "BF",
        "B": "FF",
        "r": 170,
        "g": 191,
        "b": 255
    },
    "162": {
        "R": 0,
        "G": "2E",
        "B": "BD",
        "r": 0,
        "g": 46,
        "b": 189
    },
    "163": {
        "R": "7E",
        "G": "8D",
        "B": "BD",
        "r": 126,
        "g": 141,
        "b": 189
    },
    "164": {
        "R": 0,
        "G": "1F",
        "B": 81,
        "r": 0,
        "g": 31,
        "b": 129
    },
    "165": {
        "R": 56,
        "G": 60,
        "B": 81,
        "r": 86,
        "g": 96,
        "b": 129
    },
    "166": {
        "R": 0,
        "G": 19,
        "B": 68,
        "r": 0,
        "g": 25,
        "b": 104
    },
    "167": {
        "R": 45,
        "G": "4E",
        "B": 68,
        "r": 69,
        "g": 78,
        "b": 104
    },
    "168": {
        "R": 0,
        "G": 13,
        "B": "4F",
        "r": 0,
        "g": 19,
        "b": 79
    },
    "169": {
        "R": 35,
        "G": "3B",
        "B": "4F",
        "r": 53,
        "g": 59,
        "b": 79
    },
    "170": {
        "R": 0,
        "G": 0,
        "B": "FF",
        "r": 0,
        "g": 0,
        "b": 255
    },
    "171": {
        "R": "AA",
        "G": "AA",
        "B": "FF",
        "r": 170,
        "g": 170,
        "b": 255
    },
    "172": {
        "R": 0,
        "G": 0,
        "B": "BD",
        "r": 0,
        "g": 0,
        "b": 189
    },
    "173": {
        "R": "7E",
        "G": "7E",
        "B": "BD",
        "r": 126,
        "g": 126,
        "b": 189
    },
    "174": {
        "R": 0,
        "G": 0,
        "B": 81,
        "r": 0,
        "g": 0,
        "b": 129
    },
    "175": {
        "R": 56,
        "G": 56,
        "B": 81,
        "r": 86,
        "g": 86,
        "b": 129
    },
    "176": {
        "R": 0,
        "G": 0,
        "B": 68,
        "r": 0,
        "g": 0,
        "b": 104
    },
    "177": {
        "R": 45,
        "G": 45,
        "B": 68,
        "r": 69,
        "g": 69,
        "b": 104
    },
    "178": {
        "R": 0,
        "G": 0,
        "B": "4F",
        "r": 0,
        "g": 0,
        "b": 79
    },
    "179": {
        "R": 35,
        "G": 35,
        "B": "4F",
        "r": 53,
        "g": 53,
        "b": 79
    },
    "180": {
        "R": "3F",
        "G": 0,
        "B": "FF",
        "r": 63,
        "g": 0,
        "b": 255
    },
    "181": {
        "R": "BF",
        "G": "AA",
        "B": "FF",
        "r": 191,
        "g": 170,
        "b": 255
    },
    "182": {
        "R": "2E",
        "G": 0,
        "B": "BD",
        "r": 46,
        "g": 0,
        "b": 189
    },
    "183": {
        "R": "8D",
        "G": "7E",
        "B": "BD",
        "r": 141,
        "g": 126,
        "b": 189
    },
    "184": {
        "R": "1F",
        "G": 0,
        "B": 81,
        "r": 31,
        "g": 0,
        "b": 129
    },
    "185": {
        "R": 60,
        "G": 56,
        "B": 81,
        "r": 96,
        "g": 86,
        "b": 129
    },
    "186": {
        "R": 19,
        "G": 0,
        "B": 68,
        "r": 25,
        "g": 0,
        "b": 104
    },
    "187": {
        "R": "4E",
        "G": 45,
        "B": 68,
        "r": 78,
        "g": 69,
        "b": 104
    },
    "188": {
        "R": 13,
        "G": 0,
        "B": "4F",
        "r": 19,
        "g": 0,
        "b": 79
    },
    "189": {
        "R": "3B",
        "G": 35,
        "B": "4F",
        "r": 59,
        "g": 53,
        "b": 79
    },
    "190": {
        "R": "7F",
        "G": 0,
        "B": "FF",
        "r": 127,
        "g": 0,
        "b": 255
    },
    "191": {
        "R": "D4",
        "G": "AA",
        "B": "FF",
        "r": 212,
        "g": 170,
        "b": 255
    },
    "192": {
        "R": "5E",
        "G": 0,
        "B": "BD",
        "r": 94,
        "g": 0,
        "b": 189
    },
    "193": {
        "R": "9D",
        "G": "7E",
        "B": "BD",
        "r": 157,
        "g": 126,
        "b": 189
    },
    "194": {
        "R": 40,
        "G": 0,
        "B": 81,
        "r": 64,
        "g": 0,
        "b": 129
    },
    "195": {
        "R": "6B",
        "G": 56,
        "B": 81,
        "r": 107,
        "g": 86,
        "b": 129
    },
    "196": {
        "R": 34,
        "G": 0,
        "B": 68,
        "r": 52,
        "g": 0,
        "b": 104
    },
    "197": {
        "R": 56,
        "G": 45,
        "B": 68,
        "r": 86,
        "g": 69,
        "b": 104
    },
    "198": {
        "R": 27,
        "G": 0,
        "B": "4F",
        "r": 39,
        "g": 0,
        "b": 79
    },
    "199": {
        "R": 42,
        "G": 35,
        "B": "4F",
        "r": 66,
        "g": 53,
        "b": 79
    },
    "200": {
        "R": "BF",
        "G": 0,
        "B": "FF",
        "r": 191,
        "g": 0,
        "b": 255
    },
    "201": {
        "R": "EA",
        "G": "AA",
        "B": "FF",
        "r": 234,
        "g": 170,
        "b": 255
    },
    "202": {
        "R": "8D",
        "G": 0,
        "B": "BD",
        "r": 141,
        "g": 0,
        "b": 189
    },
    "203": {
        "R": "AD",
        "G": "7E",
        "B": "BD",
        "r": 173,
        "g": 126,
        "b": 189
    },
    "204": {
        "R": 60,
        "G": 0,
        "B": 81,
        "r": 96,
        "g": 0,
        "b": 129
    },
    "205": {
        "R": 76,
        "G": 56,
        "B": 81,
        "r": 118,
        "g": 86,
        "b": 129
    },
    "206": {
        "R": "4E",
        "G": 0,
        "B": 68,
        "r": 78,
        "g": 0,
        "b": 104
    },
    "207": {
        "R": "5F",
        "G": 45,
        "B": 68,
        "r": 95,
        "g": 69,
        "b": 104
    },
    "208": {
        "R": "3B",
        "G": 0,
        "B": "4F",
        "r": 59,
        "g": 0,
        "b": 79
    },
    "209": {
        "R": 49,
        "G": 35,
        "B": "4F",
        "r": 73,
        "g": 53,
        "b": 79
    },
    "210": {
        "R": "FF",
        "G": 0,
        "B": "FF",
        "r": 255,
        "g": 0,
        "b": 255
    },
    "211": {
        "R": "FF",
        "G": "AA",
        "B": "FF",
        "r": 255,
        "g": 170,
        "b": 255
    },
    "212": {
        "R": "BD",
        "G": 0,
        "B": "BD",
        "r": 189,
        "g": 0,
        "b": 189
    },
    "213": {
        "R": "BD",
        "G": "7E",
        "B": "BD",
        "r": 189,
        "g": 126,
        "b": 189
    },
    "214": {
        "R": 81,
        "G": 0,
        "B": 81,
        "r": 129,
        "g": 0,
        "b": 129
    },
    "215": {
        "R": 81,
        "G": 56,
        "B": 81,
        "r": 129,
        "g": 86,
        "b": 129
    },
    "216": {
        "R": 68,
        "G": 0,
        "B": 68,
        "r": 104,
        "g": 0,
        "b": 104
    },
    "217": {
        "R": 68,
        "G": 45,
        "B": 68,
        "r": 104,
        "g": 69,
        "b": 104
    },
    "218": {
        "R": "4F",
        "G": 0,
        "B": "4F",
        "r": 79,
        "g": 0,
        "b": 79
    },
    "219": {
        "R": "4F",
        "G": 35,
        "B": "4F",
        "r": 79,
        "g": 53,
        "b": 79
    },
    "220": {
        "R": "FF",
        "G": 0,
        "B": "BF",
        "r": 255,
        "g": 0,
        "b": 191
    },
    "221": {
        "R": "FF",
        "G": "AA",
        "B": "EA",
        "r": 255,
        "g": 170,
        "b": 234
    },
    "222": {
        "R": "BD",
        "G": 0,
        "B": "8D",
        "r": 189,
        "g": 0,
        "b": 141
    },
    "223": {
        "R": "BD",
        "G": "7E",
        "B": "AD",
        "r": 189,
        "g": 126,
        "b": 173
    },
    "224": {
        "R": 81,
        "G": 0,
        "B": 60,
        "r": 129,
        "g": 0,
        "b": 96
    },
    "225": {
        "R": 81,
        "G": 56,
        "B": 76,
        "r": 129,
        "g": 86,
        "b": 118
    },
    "226": {
        "R": 68,
        "G": 0,
        "B": "4E",
        "r": 104,
        "g": 0,
        "b": 78
    },
    "227": {
        "R": 68,
        "G": 45,
        "B": "5F",
        "r": 104,
        "g": 69,
        "b": 95
    },
    "228": {
        "R": "4F",
        "G": 0,
        "B": "3B",
        "r": 79,
        "g": 0,
        "b": 59
    },
    "229": {
        "R": "4F",
        "G": 35,
        "B": 49,
        "r": 79,
        "g": 53,
        "b": 73
    },
    "230": {
        "R": "FF",
        "G": 0,
        "B": "7F",
        "r": 255,
        "g": 0,
        "b": 127
    },
    "231": {
        "R": "FF",
        "G": "AA",
        "B": "D4",
        "r": 255,
        "g": 170,
        "b": 212
    },
    "232": {
        "R": "BD",
        "G": 0,
        "B": "5E",
        "r": 189,
        "g": 0,
        "b": 94
    },
    "233": {
        "R": "BD",
        "G": "7E",
        "B": "9D",
        "r": 189,
        "g": 126,
        "b": 157
    },
    "234": {
        "R": 81,
        "G": 0,
        "B": 40,
        "r": 129,
        "g": 0,
        "b": 64
    },
    "235": {
        "R": 81,
        "G": 56,
        "B": "6B",
        "r": 129,
        "g": 86,
        "b": 107
    },
    "236": {
        "R": 68,
        "G": 0,
        "B": 34,
        "r": 104,
        "g": 0,
        "b": 52
    },
    "237": {
        "R": 68,
        "G": 45,
        "B": 56,
        "r": 104,
        "g": 69,
        "b": 86
    },
    "238": {
        "R": "4F",
        "G": 0,
        "B": 27,
        "r": 79,
        "g": 0,
        "b": 39
    },
    "239": {
        "R": "4F",
        "G": 35,
        "B": 42,
        "r": 79,
        "g": 53,
        "b": 66
    },
    "240": {
        "R": "FF",
        "G": 0,
        "B": "3F",
        "r": 255,
        "g": 0,
        "b": 63
    },
    "241": {
        "R": "FF",
        "G": "AA",
        "B": "BF",
        "r": 255,
        "g": 170,
        "b": 191
    },
    "242": {
        "R": "BD",
        "G": 0,
        "B": "2E",
        "r": 189,
        "g": 0,
        "b": 46
    },
    "243": {
        "R": "BD",
        "G": "7E",
        "B": "8D",
        "r": 189,
        "g": 126,
        "b": 141
    },
    "244": {
        "R": 81,
        "G": 0,
        "B": "1F",
        "r": 129,
        "g": 0,
        "b": 31
    },
    "245": {
        "R": 81,
        "G": 56,
        "B": 60,
        "r": 129,
        "g": 86,
        "b": 96
    },
    "246": {
        "R": 68,
        "G": 0,
        "B": 19,
        "r": 104,
        "g": 0,
        "b": 25
    },
    "247": {
        "R": 68,
        "G": 45,
        "B": "4E",
        "r": 104,
        "g": 69,
        "b": 78
    },
    "248": {
        "R": "4F",
        "G": 0,
        "B": 13,
        "r": 79,
        "g": 0,
        "b": 19
    },
    "249": {
        "R": "4F",
        "G": 35,
        "B": "3B",
        "r": 79,
        "g": 53,
        "b": 59
    },
    "250": {
        "R": 33,
        "G": 33,
        "B": 33,
        "r": 51,
        "g": 51,
        "b": 51
    },
    "251": {
        "R": 50,
        "G": 50,
        "B": 50,
        "r": 80,
        "g": 80,
        "b": 80
    },
    "252": {
        "R": 69,
        "G": 69,
        "B": 69,
        "r": 105,
        "g": 105,
        "b": 105
    },
    "253": {
        "R": 82,
        "G": 82,
        "B": 82,
        "r": 130,
        "g": 130,
        "b": 130
    },
    "254": {
        "R": "BE",
        "G": "BE",
        "B": "BE",
        "r": 190,
        "g": 190,
        "b": 190
    },
    "255": {
        "R": "FF",
        "G": "FF",
        "B": "FF",
        "r": 255,
        "g": 255,
        "b": 255
    }
}